README.rst
setup.cfg
setup.py
seamless/__init__.py
seamless/cli.py
seamless/requests.py
seamless/signer.py
seamless/wsgi.py
seamless.egg-info/PKG-INFO
seamless.egg-info/SOURCES.txt
seamless.egg-info/dependency_links.txt
seamless.egg-info/entry_points.txt
seamless.egg-info/requires.txt
seamless.egg-info/top_level.txt