Metadata-Version: 1.1
Name: seamless
Version: 0.1.0
Summary: UNKNOWN
Home-page: http://github.com/emulbreh/seamless/
Author: Johannes Dollinger
Author-email: emulbreh@googlemail.com
License: BSD
Platform: UNKNOWN
Classifier: Development Status :: 3 - Alpha
Classifier: Intended Audience :: Developers
Classifier: License :: OSI Approved :: BSD License
Classifier: Operating System :: POSIX :: Linux
Classifier: Operating System :: OS Independent
Classifier: Programming Language :: Python :: 2.7
Classifier: Programming Language :: Python :: 3
